admetica/__init__.py
admetica/admetica.py
admetica/constants.py
admetica/Models/CL-Hepa.ckpt
admetica/Models/CL-Micro.ckpt
admetica/Models/CYP1A2-Inhibitor.ckpt
admetica/Models/CYP1A2-Substrate.ckpt
admetica/Models/CYP2C19-Inhibitor.ckpt
admetica/Models/CYP2C19-Substrate.ckpt
admetica/Models/CYP2C9-Inhibitor.ckpt
admetica/Models/CYP2C9-Substrate.ckpt
admetica/Models/CYP2D6-Inhibitor.ckpt
admetica/Models/CYP2D6-Substrate.ckpt
admetica/Models/Caco2.ckpt
admetica/Models/Half-Life.ckpt
admetica/Models/Lipophilicity.ckpt
admetica/Models/PPBR.ckpt
admetica/Models/Solubility.ckpt
admetica/Models/VDss.ckpt
cli/__init__.py
cli/cli.py
admetica-1.0.dist-info/METADATA
admetica-1.0.dist-info/WHEEL
admetica-1.0.dist-info/entry_points.txt
admetica-1.0.dist-info/top_level.txt
admetica-1.0.dist-info/RECORD
