Metadata-Version: 2.1
Name: admetica
Version: 1.0
Requires-Dist: aimsim-core ==2.2.1
Requires-Dist: aiohttp ==3.9.5
Requires-Dist: aiosignal ==1.3.1
Requires-Dist: astartes ==1.2.2
Requires-Dist: attrs ==23.2.0
Requires-Dist: blinker ==1.8.2
Requires-Dist: chemprop ==2.0.0
Requires-Dist: click ==8.1.7
Requires-Dist: ConfigArgParse ==1.7
Requires-Dist: dill ==0.3.8
Requires-Dist: filelock ==3.15.4
Requires-Dist: Flask ==3.0.3
Requires-Dist: frozenlist ==1.4.1
Requires-Dist: fsspec ==2024.6.1
Requires-Dist: idna ==3.7
Requires-Dist: itsdangerous ==2.2.0
Requires-Dist: Jinja2 ==3.1.4
Requires-Dist: joblib ==1.4.2
Requires-Dist: lightning ==2.3.3
Requires-Dist: lightning-utilities ==0.11.6
Requires-Dist: MarkupSafe ==2.1.5
Requires-Dist: mhfp ==1.9.6
Requires-Dist: mordredcommunity ==2.0.6
Requires-Dist: mpmath ==1.3.0
Requires-Dist: multidict ==6.0.5
Requires-Dist: multiprocess ==0.70.16
Requires-Dist: networkx ==3.3
Requires-Dist: numpy ==1.26.4
Requires-Dist: packaging ==24.1
Requires-Dist: padelpy ==0.1.16
Requires-Dist: pandas ==2.2.2
Requires-Dist: pillow ==10.4.0
Requires-Dist: psutil ==6.0.0
Requires-Dist: python-dateutil ==2.9.0.post0
Requires-Dist: pytorch-lightning ==2.3.3
Requires-Dist: pytz ==2024.1
Requires-Dist: PyYAML ==6.0.1
Requires-Dist: rdkit ==2024.3.3
Requires-Dist: scikit-learn ==1.5.1
Requires-Dist: scipy ==1.14.0
Requires-Dist: setuptools ==72.1.0
Requires-Dist: six ==1.16.0
Requires-Dist: sympy ==1.13.1
Requires-Dist: tabulate ==0.9.0
Requires-Dist: threadpoolctl ==3.5.0
Requires-Dist: torch ==2.4.0
Requires-Dist: torchmetrics ==1.4.0.post0
Requires-Dist: tqdm ==4.66.4
Requires-Dist: typing-extensions ==4.12.2
Requires-Dist: tzdata ==2024.1
Requires-Dist: Werkzeug ==3.0.3
Requires-Dist: yarl ==1.9.4
